google/apps/chat/__init__.py
google/apps/chat/gapic_version.py
google/apps/chat/py.typed
google/apps/chat_v1/__init__.py
google/apps/chat_v1/gapic_metadata.json
google/apps/chat_v1/gapic_version.py
google/apps/chat_v1/py.typed
google/apps/chat_v1/services/__init__.py
google/apps/chat_v1/services/chat_service/__init__.py
google/apps/chat_v1/services/chat_service/async_client.py
google/apps/chat_v1/services/chat_service/client.py
google/apps/chat_v1/services/chat_service/pagers.py
google/apps/chat_v1/services/chat_service/transports/__init__.py
google/apps/chat_v1/services/chat_service/transports/base.py
google/apps/chat_v1/services/chat_service/transports/grpc.py
google/apps/chat_v1/services/chat_service/transports/grpc_asyncio.py
google/apps/chat_v1/services/chat_service/transports/rest.py
google/apps/chat_v1/services/chat_service/transports/rest_base.py
google/apps/chat_v1/types/__init__.py
google/apps/chat_v1/types/action_status.py
google/apps/chat_v1/types/annotation.py
google/apps/chat_v1/types/attachment.py
google/apps/chat_v1/types/chat_service.py
google/apps/chat_v1/types/contextual_addon.py
google/apps/chat_v1/types/deletion_metadata.py
google/apps/chat_v1/types/event_payload.py
google/apps/chat_v1/types/group.py
google/apps/chat_v1/types/history_state.py
google/apps/chat_v1/types/matched_url.py
google/apps/chat_v1/types/membership.py
google/apps/chat_v1/types/message.py
google/apps/chat_v1/types/reaction.py
google/apps/chat_v1/types/slash_command.py
google/apps/chat_v1/types/space.py
google/apps/chat_v1/types/space_event.py
google/apps/chat_v1/types/space_notification_setting.py
google/apps/chat_v1/types/space_read_state.py
google/apps/chat_v1/types/space_setup.py
google/apps/chat_v1/types/thread_read_state.py
google/apps/chat_v1/types/user.py
google/apps/chat_v1/types/widgets.py
google_apps_chat-0.5.0.dist-info/licenses/LICENSE
google_apps_chat-0.5.0.dist-info/METADATA
google_apps_chat-0.5.0.dist-info/WHEEL
google_apps_chat-0.5.0.dist-info/top_level.txt
google_apps_chat-0.5.0.dist-info/RECORD
